{
    "output_dir": "grid-ho",
    "dataset_type": "sample",
    "dataset": "MultiUnique",
    "model": "agglomerative",
    "linkage": "average",
    "embedding": "MultiSource-full-cdk10-m0.5-e5-b128-L6",
    "threshold": 0.06,
    "sample_order": "asc",
    "sample_size": 11949,
    "held_out": true,
    "device": "cuda",
    "overwrite": false,
    "normalize_embedding": false,
    "seed": 42,
    "train_started_at": "2025-11-20 23:34:26.434538",
    "train_end_at": "2025-11-20 23:34:34.043535",
    "duration": "7608.997 miliseconds",
    "eval_start_at": "2025-11-20 23:34:34.043965",
    "eval_end_at": "2025-11-20 23:34:34.227666",
    "eval_duration": "183.701 miliseconds",
    "eval_score": {
        "f1_group_accuracy": "0.999",
        "group_accuracy": "0.9",
        "singleton_f1": "0.696",
        "num_cluster": "153",
        "ami_score": "0.999",
        "nmi_score": "0.999",
        "ari_score": "0.999",
        "hgi_score": "1.0",
        "cpi_score": "0.999",
        "vmi_score": "0.999",
        "fmi_score": "0.999"
    }
}