{
    "output_dir": "effect-k",
    "dataset_type": "sample",
    "dataset": "Thunderbird",
    "model": "agglomerative",
    "linkage": "average",
    "embedding": "MultiSource-full-crk0-m0.5-e5-b128-L6",
    "threshold": 0.1,
    "sample_order": "asc",
    "sample_size": 2000,
    "held_out": true,
    "overwrite": false,
    "normalize_embedding": false,
    "seed": 42,
    "train_started_at": "2025-11-20 09:42:15.770524",
    "train_end_at": "2025-11-20 09:42:19.643115",
    "duration": "3872.591 miliseconds",
    "eval_start_at": "2025-11-20 09:42:19.643629",
    "eval_end_at": "2025-11-20 09:42:19.753686",
    "eval_duration": "110.057 miliseconds",
    "eval_score": {
        "f1_group_accuracy": "0.998",
        "group_accuracy": "0.653",
        "singleton_f1": "0.893",
        "num_cluster": "176",
        "ami_score": "0.979",
        "nmi_score": "0.983",
        "ari_score": "0.998",
        "hgi_score": "0.998",
        "cpi_score": "0.968",
        "vmi_score": "0.983",
        "fmi_score": "0.998"
    }
}