{
    "output_dir": "effect-base",
    "dataset_type": "sample",
    "dataset": "Proxifier",
    "model": "agglomerative",
    "linkage": "average",
    "embedding": "all-MiniLM-L6-v2",
    "threshold": 0.16,
    "sample_order": "asc",
    "sample_size": 2000,
    "held_out": false,
    "device": "cuda",
    "overwrite": false,
    "normalize_embedding": false,
    "seed": 42,
    "train_started_at": "2025-11-21 15:40:05.547107",
    "train_end_at": "2025-11-21 15:40:09.062601",
    "duration": "3515.494 miliseconds",
    "eval_start_at": "2025-11-21 15:40:09.063302",
    "eval_end_at": "2025-11-21 15:40:09.145500",
    "eval_duration": "82.198 miliseconds",
    "eval_score": {
        "f1_group_accuracy": "0.4",
        "group_accuracy": "0.001",
        "singleton_f1": "0",
        "num_cluster": "222",
        "ami_score": "0.372",
        "nmi_score": "0.411",
        "ari_score": "0.267",
        "hgi_score": "0.973",
        "cpi_score": "0.261",
        "vmi_score": "0.411",
        "fmi_score": "0.499"
    }
}