{
    "output_dir": "effect-base",
    "dataset_type": "sample",
    "dataset": "Linux",
    "model": "agglomerative",
    "linkage": "average",
    "embedding": "all-distilroberta-v1",
    "threshold": 0.01,
    "sample_order": "asc",
    "sample_size": 2000,
    "held_out": false,
    "device": "cuda",
    "overwrite": false,
    "normalize_embedding": false,
    "seed": 42,
    "train_started_at": "2025-11-21 19:16:07.558985",
    "train_end_at": "2025-11-21 19:16:11.250072",
    "duration": "3691.087 miliseconds",
    "eval_start_at": "2025-11-21 19:16:11.250770",
    "eval_end_at": "2025-11-21 19:16:11.346319",
    "eval_duration": "95.549 miliseconds",
    "eval_score": {
        "f1_group_accuracy": "0.195",
        "group_accuracy": "0.182",
        "singleton_f1": "0.964",
        "num_cluster": "189",
        "ami_score": "0.591",
        "nmi_score": "0.661",
        "ari_score": "0.153",
        "hgi_score": "1.0",
        "cpi_score": "0.493",
        "vmi_score": "0.661",
        "fmi_score": "0.328"
    }
}