{
    "output_dir": "effect-k",
    "dataset_type": "sample",
    "dataset": "OpenStack",
    "model": "agglomerative",
    "linkage": "average",
    "embedding": "MultiSource-full-crk0-m0.5-e5-b128-L6",
    "threshold": 0.04,
    "sample_order": "asc",
    "sample_size": 2000,
    "held_out": false,
    "overwrite": false,
    "normalize_embedding": false,
    "seed": 42,
    "train_started_at": "2025-11-19 17:21:09.413733",
    "train_end_at": "2025-11-19 17:21:13.479706",
    "duration": "4065.973 miliseconds",
    "eval_start_at": "2025-11-19 17:21:13.480226",
    "eval_end_at": "2025-11-19 17:21:13.596615",
    "eval_duration": "116.389 miliseconds",
    "eval_score": {
        "f1_group_accuracy": "0.489",
        "group_accuracy": "0.213",
        "singleton_f1": "0.044",
        "num_cluster": "244",
        "ami_score": "0.734",
        "nmi_score": "0.793",
        "ari_score": "0.425",
        "hgi_score": "0.999",
        "cpi_score": "0.657",
        "vmi_score": "0.793",
        "fmi_score": "0.569"
    }
}