{
    "output_dir": "effect-base",
    "dataset_type": "sample",
    "dataset": "MultiSource",
    "model": "agglomerative",
    "linkage": "average",
    "embedding": "all-distilroberta-v1",
    "threshold": 0.22,
    "sample_order": "asc",
    "sample_size": 32000,
    "held_out": false,
    "device": "cuda",
    "overwrite": false,
    "normalize_embedding": false,
    "seed": 42,
    "train_started_at": "2025-11-21 19:57:01.073497",
    "train_end_at": "2025-11-21 19:57:38.642239",
    "duration": "37568.742 miliseconds",
    "eval_start_at": "2025-11-21 19:57:38.642808",
    "eval_end_at": "2025-11-21 19:57:41.345955",
    "eval_duration": "2703.147 miliseconds",
    "eval_score": {
        "f1_group_accuracy": "0.864",
        "group_accuracy": "0.528",
        "singleton_f1": "0.739",
        "num_cluster": "1327",
        "ami_score": "0.954",
        "nmi_score": "0.964",
        "ari_score": "0.863",
        "hgi_score": "0.969",
        "cpi_score": "0.959",
        "vmi_score": "0.964",
        "fmi_score": "0.865"
    }
}