{
    "output_dir": "effect-base",
    "dataset_type": "sample",
    "dataset": "Proxifier",
    "model": "agglomerative",
    "linkage": "average",
    "embedding": "all-MiniLM-L6-v2",
    "threshold": 0.14,
    "sample_order": "asc",
    "sample_size": 2000,
    "held_out": false,
    "device": "cuda",
    "overwrite": false,
    "normalize_embedding": false,
    "seed": 42,
    "train_started_at": "2025-11-21 15:39:55.008550",
    "train_end_at": "2025-11-21 15:39:58.484542",
    "duration": "3475.992 miliseconds",
    "eval_start_at": "2025-11-21 15:39:58.485241",
    "eval_end_at": "2025-11-21 15:39:58.572777",
    "eval_duration": "87.536 miliseconds",
    "eval_score": {
        "f1_group_accuracy": "0.395",
        "group_accuracy": "0.001",
        "singleton_f1": "0",
        "num_cluster": "243",
        "ami_score": "0.365",
        "nmi_score": "0.407",
        "ari_score": "0.263",
        "hgi_score": "0.98",
        "cpi_score": "0.256",
        "vmi_score": "0.407",
        "fmi_score": "0.496"
    }
}