{
    "output_dir": "grid-ho",
    "dataset_type": "sample",
    "dataset": "Zookeeper",
    "model": "agglomerative",
    "linkage": "average",
    "embedding": "MultiSource-full-crk1-m0.5-e5-b128-L6",
    "threshold": 0.12,
    "sample_order": "asc",
    "sample_size": 919,
    "held_out": true,
    "device": "cuda",
    "overwrite": false,
    "normalize_embedding": false,
    "seed": 42,
    "train_started_at": "2025-11-20 16:48:28.629409",
    "train_end_at": "2025-11-20 16:48:32.286346",
    "duration": "3656.937 miliseconds",
    "eval_start_at": "2025-11-20 16:48:32.286831",
    "eval_end_at": "2025-11-20 16:48:32.312246",
    "eval_duration": "25.415 miliseconds",
    "eval_score": {
        "f1_group_accuracy": "1.0",
        "group_accuracy": "0.989",
        "singleton_f1": "0.667",
        "num_cluster": "23",
        "ami_score": "0.997",
        "nmi_score": "0.997",
        "ari_score": "1.0",
        "hgi_score": "1.0",
        "cpi_score": "0.995",
        "vmi_score": "0.997",
        "fmi_score": "1.0"
    }
}