{
    "output_dir": "effect-base",
    "dataset_type": "sample",
    "dataset": "Spark",
    "model": "agglomerative",
    "linkage": "average",
    "embedding": "all-MiniLM-L6-v2",
    "threshold": 0.07,
    "sample_order": "asc",
    "sample_size": 2000,
    "held_out": false,
    "device": "cuda",
    "overwrite": false,
    "normalize_embedding": false,
    "seed": 42,
    "train_started_at": "2025-11-21 15:41:57.964020",
    "train_end_at": "2025-11-21 15:42:01.331112",
    "duration": "3367.092 miliseconds",
    "eval_start_at": "2025-11-21 15:42:01.331819",
    "eval_end_at": "2025-11-21 15:42:01.439756",
    "eval_duration": "107.937 miliseconds",
    "eval_score": {
        "f1_group_accuracy": "0.559",
        "group_accuracy": "0.08",
        "singleton_f1": "0.297",
        "num_cluster": "281",
        "ami_score": "0.64",
        "nmi_score": "0.702",
        "ari_score": "0.525",
        "hgi_score": "1.0",
        "cpi_score": "0.541",
        "vmi_score": "0.702",
        "fmi_score": "0.623"
    }
}