{
    "output_dir": "effect-base",
    "dataset_type": "sample",
    "dataset": "Thunderbird",
    "model": "agglomerative",
    "linkage": "average",
    "embedding": "all-MiniLM-L12-v2",
    "threshold": 0.14,
    "sample_order": "asc",
    "sample_size": 2000,
    "held_out": false,
    "device": "cuda",
    "overwrite": false,
    "normalize_embedding": false,
    "seed": 42,
    "train_started_at": "2025-11-21 16:55:09.042891",
    "train_end_at": "2025-11-21 16:55:13.068652",
    "duration": "4025.761 miliseconds",
    "eval_start_at": "2025-11-21 16:55:13.069338",
    "eval_end_at": "2025-11-21 16:55:13.161031",
    "eval_duration": "91.693 miliseconds",
    "eval_score": {
        "f1_group_accuracy": "0.998",
        "group_accuracy": "0.656",
        "singleton_f1": "0.819",
        "num_cluster": "183",
        "ami_score": "0.973",
        "nmi_score": "0.978",
        "ari_score": "0.997",
        "hgi_score": "0.994",
        "cpi_score": "0.962",
        "vmi_score": "0.978",
        "fmi_score": "0.998"
    }
}