{
    "output_dir": "effect-base",
    "dataset_type": "sample",
    "dataset": "MultiSource",
    "model": "agglomerative",
    "linkage": "average",
    "embedding": "all-MiniLM-L12-v2",
    "threshold": 0.25,
    "sample_order": "asc",
    "sample_size": 32000,
    "held_out": false,
    "device": "cuda",
    "overwrite": false,
    "normalize_embedding": false,
    "seed": 42,
    "train_started_at": "2025-11-21 17:18:26.542588",
    "train_end_at": "2025-11-21 17:19:01.595600",
    "duration": "35053.012 miliseconds",
    "eval_start_at": "2025-11-21 17:19:01.596166",
    "eval_end_at": "2025-11-21 17:19:04.246147",
    "eval_duration": "2649.981 miliseconds",
    "eval_score": {
        "f1_group_accuracy": "0.89",
        "group_accuracy": "0.546",
        "singleton_f1": "0.715",
        "num_cluster": "1287",
        "ami_score": "0.957",
        "nmi_score": "0.966",
        "ari_score": "0.888",
        "hgi_score": "0.968",
        "cpi_score": "0.964",
        "vmi_score": "0.966",
        "fmi_score": "0.89"
    }
}