{
    "output_dir": "effect-base",
    "dataset_type": "sample",
    "dataset": "Android",
    "model": "agglomerative",
    "linkage": "average",
    "embedding": "all-MiniLM-L6-v2",
    "threshold": 0.02,
    "sample_order": "asc",
    "sample_size": 2000,
    "held_out": false,
    "device": "cuda",
    "overwrite": false,
    "normalize_embedding": false,
    "seed": 42,
    "train_started_at": "2025-11-21 15:12:36.835129",
    "train_end_at": "2025-11-21 15:12:40.318070",
    "duration": "3482.941 miliseconds",
    "eval_start_at": "2025-11-21 15:12:40.318764",
    "eval_end_at": "2025-11-21 15:12:40.421713",
    "eval_duration": "102.949 miliseconds",
    "eval_score": {
        "f1_group_accuracy": "0.948",
        "group_accuracy": "0.655",
        "singleton_f1": "0.57",
        "num_cluster": "242",
        "ami_score": "0.947",
        "nmi_score": "0.963",
        "ari_score": "0.946",
        "hgi_score": "0.998",
        "cpi_score": "0.93",
        "vmi_score": "0.963",
        "fmi_score": "0.949"
    }
}