{
    "output_dir": "effect-base",
    "dataset_type": "sample",
    "dataset": "HDFS",
    "model": "agglomerative",
    "linkage": "average",
    "embedding": "all-distilroberta-v1",
    "threshold": 0.04,
    "sample_order": "asc",
    "sample_size": 2000,
    "held_out": false,
    "device": "cuda",
    "overwrite": false,
    "normalize_embedding": false,
    "seed": 42,
    "train_started_at": "2025-11-21 19:08:13.822826",
    "train_end_at": "2025-11-21 19:08:17.973367",
    "duration": "4150.541 miliseconds",
    "eval_start_at": "2025-11-21 19:08:17.974072",
    "eval_end_at": "2025-11-21 19:08:18.002706",
    "eval_duration": "28.634 miliseconds",
    "eval_score": {
        "f1_group_accuracy": "0.922",
        "group_accuracy": "0.695",
        "singleton_f1": "0.667",
        "num_cluster": "25",
        "ami_score": "0.942",
        "nmi_score": "0.943",
        "ari_score": "0.911",
        "hgi_score": "1.0",
        "cpi_score": "0.893",
        "vmi_score": "0.943",
        "fmi_score": "0.924"
    }
}