{
    "output_dir": "effect-k",
    "dataset_type": "sample",
    "dataset": "OpenSSH",
    "model": "agglomerative",
    "linkage": "average",
    "embedding": "MultiSource-full-cdk1-m0.5-e5-b128-L6",
    "threshold": 0.16,
    "sample_order": "asc",
    "sample_size": 2000,
    "held_out": false,
    "overwrite": false,
    "normalize_embedding": false,
    "seed": 42,
    "train_started_at": "2025-11-20 02:41:40.033627",
    "train_end_at": "2025-11-20 02:41:43.965714",
    "duration": "3932.087 miliseconds",
    "eval_start_at": "2025-11-20 02:41:43.966224",
    "eval_end_at": "2025-11-20 02:41:44.007331",
    "eval_duration": "41.107 miliseconds",
    "eval_score": {
        "f1_group_accuracy": "0.995",
        "group_accuracy": "0.876",
        "singleton_f1": "0.769",
        "num_cluster": "34",
        "ami_score": "0.988",
        "nmi_score": "0.988",
        "ari_score": "0.994",
        "hgi_score": "1.0",
        "cpi_score": "0.977",
        "vmi_score": "0.988",
        "fmi_score": "0.995"
    }
}