{
    "output_dir": "effect-base",
    "dataset_type": "sample",
    "dataset": "Mac",
    "model": "agglomerative",
    "linkage": "average",
    "embedding": "all-MiniLM-L12-v2",
    "threshold": 0.07,
    "sample_order": "asc",
    "sample_size": 2000,
    "held_out": false,
    "device": "cuda",
    "overwrite": false,
    "normalize_embedding": false,
    "seed": 42,
    "train_started_at": "2025-11-21 16:40:45.350920",
    "train_end_at": "2025-11-21 16:40:49.046249",
    "duration": "3695.329 miliseconds",
    "eval_start_at": "2025-11-21 16:40:49.046956",
    "eval_end_at": "2025-11-21 16:40:49.202944",
    "eval_duration": "155.988 miliseconds",
    "eval_score": {
        "f1_group_accuracy": "0.724",
        "group_accuracy": "0.741",
        "singleton_f1": "0.894",
        "num_cluster": "357",
        "ami_score": "0.941",
        "nmi_score": "0.972",
        "ari_score": "0.721",
        "hgi_score": "0.987",
        "cpi_score": "0.958",
        "vmi_score": "0.972",
        "fmi_score": "0.745"
    }
}