{
    "output_dir": "grid-ho",
    "dataset_type": "sample",
    "dataset": "MultiUnique",
    "model": "agglomerative",
    "linkage": "average",
    "embedding": "MultiSource-full-crk0-m0.5-e5-b128-L6",
    "threshold": 0.22,
    "sample_order": "asc",
    "sample_size": 15482,
    "held_out": true,
    "device": "cuda",
    "overwrite": false,
    "normalize_embedding": false,
    "seed": 42,
    "train_started_at": "2025-11-20 15:39:05.825286",
    "train_end_at": "2025-11-20 15:39:20.331694",
    "duration": "14506.408 miliseconds",
    "eval_start_at": "2025-11-20 15:39:20.332115",
    "eval_end_at": "2025-11-20 15:39:22.328168",
    "eval_duration": "1996.053 miliseconds",
    "eval_score": {
        "f1_group_accuracy": "0.865",
        "group_accuracy": "0.5",
        "singleton_f1": "0.824",
        "num_cluster": "1301",
        "ami_score": "0.955",
        "nmi_score": "0.967",
        "ari_score": "0.863",
        "hgi_score": "0.977",
        "cpi_score": "0.957",
        "vmi_score": "0.967",
        "fmi_score": "0.867"
    }
}