{
    "output_dir": "effect-base",
    "dataset_type": "sample",
    "dataset": "MultiSource",
    "model": "agglomerative",
    "linkage": "average",
    "embedding": "MultiSource-full-cdk3-m0.5-e5-b16-distilroberta",
    "threshold": 0.27,
    "sample_order": "asc",
    "sample_size": 32000,
    "held_out": false,
    "device": "cuda",
    "overwrite": false,
    "normalize_embedding": false,
    "seed": 42,
    "train_started_at": "2025-11-22 18:06:28.757077",
    "train_end_at": "2025-11-22 18:07:08.302401",
    "duration": "39545.324 miliseconds",
    "eval_start_at": "2025-11-22 18:07:08.302967",
    "eval_end_at": "2025-11-22 18:07:11.198107",
    "eval_duration": "2895.14 miliseconds",
    "eval_score": {
        "f1_group_accuracy": "0.999",
        "group_accuracy": "0.971",
        "singleton_f1": "0.981",
        "num_cluster": "1338",
        "ami_score": "0.999",
        "nmi_score": "0.999",
        "ari_score": "0.999",
        "hgi_score": "0.999",
        "cpi_score": "1.0",
        "vmi_score": "0.999",
        "fmi_score": "0.999"
    }
}