{
    "output_dir": "effect-k",
    "dataset_type": "sample",
    "dataset": "Mac",
    "model": "agglomerative",
    "linkage": "average",
    "embedding": "MultiSource-full-crk3-m0.5-e5-b128-L6",
    "threshold": 0.3,
    "sample_order": "asc",
    "sample_size": 2000,
    "held_out": false,
    "overwrite": false,
    "normalize_embedding": false,
    "seed": 42,
    "train_started_at": "2025-11-20 03:57:11.869165",
    "train_end_at": "2025-11-20 03:57:15.827486",
    "duration": "3958.321 miliseconds",
    "eval_start_at": "2025-11-20 03:57:15.828029",
    "eval_end_at": "2025-11-20 03:57:16.001108",
    "eval_duration": "173.079 miliseconds",
    "eval_score": {
        "f1_group_accuracy": "0.996",
        "group_accuracy": "0.969",
        "singleton_f1": "0.993",
        "num_cluster": "337",
        "ami_score": "0.997",
        "nmi_score": "0.999",
        "ari_score": "0.996",
        "hgi_score": "0.997",
        "cpi_score": "1.0",
        "vmi_score": "0.999",
        "fmi_score": "0.996"
    }
}