{
    "output_dir": "effect-base",
    "dataset_type": "sample",
    "dataset": "Proxifier",
    "model": "agglomerative",
    "linkage": "average",
    "embedding": "all-mpnet-base-v2",
    "threshold": 0.14,
    "sample_order": "asc",
    "sample_size": 2000,
    "held_out": false,
    "device": "cuda",
    "overwrite": false,
    "normalize_embedding": false,
    "seed": 42,
    "train_started_at": "2025-11-21 18:05:09.897619",
    "train_end_at": "2025-11-21 18:05:14.588717",
    "duration": "4691.098 miliseconds",
    "eval_start_at": "2025-11-21 18:05:14.589294",
    "eval_end_at": "2025-11-21 18:05:14.657178",
    "eval_duration": "67.884 miliseconds",
    "eval_score": {
        "f1_group_accuracy": "0.442",
        "group_accuracy": "0.001",
        "singleton_f1": "0",
        "num_cluster": "176",
        "ami_score": "0.419",
        "nmi_score": "0.451",
        "ari_score": "0.303",
        "hgi_score": "0.985",
        "cpi_score": "0.292",
        "vmi_score": "0.451",
        "fmi_score": "0.533"
    }
}