{
    "output_dir": "effect-k",
    "dataset_type": "sample",
    "dataset": "MultiUnique",
    "model": "agglomerative",
    "linkage": "average",
    "embedding": "MultiSource-full-cdk1-m0.5-e5-b128-L6",
    "threshold": 0.02,
    "sample_order": "asc",
    "sample_size": 15482,
    "held_out": false,
    "overwrite": false,
    "normalize_embedding": false,
    "seed": 42,
    "train_started_at": "2025-11-20 03:22:58.423581",
    "train_end_at": "2025-11-20 03:23:13.131829",
    "duration": "14708.248 miliseconds",
    "eval_start_at": "2025-11-20 03:23:13.132256",
    "eval_end_at": "2025-11-20 03:23:15.484161",
    "eval_duration": "2351.905 miliseconds",
    "eval_score": {
        "f1_group_accuracy": "0.98",
        "group_accuracy": "0.632",
        "singleton_f1": "0.87",
        "num_cluster": "1650",
        "ami_score": "0.98",
        "nmi_score": "0.985",
        "ari_score": "0.98",
        "hgi_score": "1.0",
        "cpi_score": "0.971",
        "vmi_score": "0.985",
        "fmi_score": "0.981"
    }
}